lshplots/__init__.py
lshplots/puffin_venn3.py
lshplots-1.0.1.dist-info/METADATA
lshplots-1.0.1.dist-info/WHEEL
lshplots-1.0.1.dist-info/top_level.txt
lshplots-1.0.1.dist-info/RECORD
